odoo/addons/l10n_th_sequence_branch/README.rst
odoo/addons/l10n_th_sequence_branch/__init__.py
odoo/addons/l10n_th_sequence_branch/__manifest__.py
odoo/addons/l10n_th_sequence_branch/i18n/l10n_th_sequence_branch.pot
odoo/addons/l10n_th_sequence_branch/models/__init__.py
odoo/addons/l10n_th_sequence_branch/models/ir_sequence.py
odoo/addons/l10n_th_sequence_branch/readme/CONTRIBUTORS.rst
odoo/addons/l10n_th_sequence_branch/readme/DESCRIPTION.rst
odoo/addons/l10n_th_sequence_branch/readme/HISTORY.rst
odoo/addons/l10n_th_sequence_branch/static/description/icon.png
odoo/addons/l10n_th_sequence_branch/static/description/index.html
odoo/addons/l10n_th_sequence_branch/tests/__init__.py
odoo/addons/l10n_th_sequence_branch/tests/test_ir_sequence.py
odoo/addons/l10n_th_sequence_branch/views/ir_sequence_view.xml
odoo14_addon_l10n_th_sequence_branch-14.0.1.0.1.dev6.dist-info/METADATA
odoo14_addon_l10n_th_sequence_branch-14.0.1.0.1.dev6.dist-info/WHEEL
odoo14_addon_l10n_th_sequence_branch-14.0.1.0.1.dev6.dist-info/top_level.txt
odoo14_addon_l10n_th_sequence_branch-14.0.1.0.1.dev6.dist-info/RECORD
